growbot/__init__.py
growbot-0.2.5.dist-info/LICENSE
growbot-0.2.5.dist-info/METADATA
growbot-0.2.5.dist-info/WHEEL
growbot-0.2.5.dist-info/top_level.txt
growbot-0.2.5.dist-info/RECORD
