Metadata-Version: 2.1
Name: growbot
Version: 0.2.5
Summary: Client library for GrowBot
Home-page: https://github.com/teamxiv/growbot-python
Author: Team xiv
Author-email: me@qaisjp.com
License: UNKNOWN
Platform: UNKNOWN
Classifier: Programming Language :: Python :: 3
Classifier: License :: OSI Approved :: MIT License
Classifier: Operating System :: OS Independent
Requires-Dist: websockets (>=7.0)
